agentdeck/__init__.py
agentdeck/config/pricing.yaml
agentdeck/controllers/__init__.py
agentdeck/controllers/action_only.py
agentdeck/controllers/reasoning.py
agentdeck/core/__init__.py
agentdeck/core/agentdeck.py
agentdeck/core/console.py
agentdeck/core/conversation.py
agentdeck/core/event_bus.py
agentdeck/core/event_factory.py
agentdeck/core/game_event_emitter.py
agentdeck/core/logging.py
agentdeck/core/match_runtime.py
agentdeck/core/prompt_builder.py
agentdeck/core/recorder.py
agentdeck/core/replay.py
agentdeck/core/replay_utils.py
agentdeck/core/session.py
agentdeck/core/state_adapter.py
agentdeck/core/types.py
agentdeck/core/base/__init__.py
agentdeck/core/base/controller.py
agentdeck/core/base/game.py
agentdeck/core/base/player.py
agentdeck/core/base/renderer.py
agentdeck/core/base/spectator.py
agentdeck/core/mechanics/__init__.py
agentdeck/core/mechanics/turn_based.py
agentdeck/games/__init__.py
agentdeck/games/examples/__init__.py
agentdeck/games/examples/fixed_damage.py
agentdeck/games/examples/hangman.py
agentdeck/monitors/__init__.py
agentdeck/monitors/base.py
agentdeck/monitors/progress.py
agentdeck/players/__init__.py
agentdeck/players/anthropic_player.py
agentdeck/players/google_player.py
agentdeck/players/llm_player.py
agentdeck/players/mock.py
agentdeck/players/openai_player.py
agentdeck/prompts/__init__.py
agentdeck/renderers/__init__.py
agentdeck/renderers/text_renderer.py
agentdeck/research/__init__.py
agentdeck/research/analysis.py
agentdeck/research/comparison.py
agentdeck/research/cost_analysis.py
agentdeck/research/multi_session.py
agentdeck/research/performance_analysis.py
agentdeck/research/statistical.py
agentdeck/research/statistical_analysis.py
agentdeck/spectators/__init__.py
agentdeck/spectators/narrator.py
agentdeck/spectators/progress.py
agentdeck/spectators/research_spectators.py
agentdeck/spectators/stats.py
agentdeck/spectators/token_usage.py
agentdeck/spectators/utils.py
agentdeck/utils/__init__.py
agentdeck/utils/pricing.py
agentdeck_ai-0.1.0rc2.dist-info/licenses/LICENSE
agentdeck_ai-0.1.0rc2.dist-info/METADATA
agentdeck_ai-0.1.0rc2.dist-info/WHEEL
agentdeck_ai-0.1.0rc2.dist-info/top_level.txt
agentdeck_ai-0.1.0rc2.dist-info/RECORD
