Metadata-Version: 2.4
Name: agentdeck-ai
Version: 0.1.0rc2
Summary: Research platform for studying AI behavior through game scenarios
Author-email: AgentDeck Team <contact@agentdeck.ai>
License: MIT
Project-URL: Homepage, https://github.com/DiegoZoracKy/agentdeck-preview
Project-URL: Documentation, https://github.com/DiegoZoracKy/agentdeck-preview#readme
Project-URL: Repository, https://github.com/DiegoZoracKy/agentdeck-preview.git
Project-URL: Issues, https://github.com/DiegoZoracKy/agentdeck-preview/issues
Classifier: Development Status :: 3 - Alpha
Classifier: Intended Audience :: Science/Research
Classifier: Intended Audience :: Developers
Classifier: License :: OSI Approved :: MIT License
Classifier: Programming Language :: Python :: 3
Classifier: Programming Language :: Python :: 3.9
Classifier: Programming Language :: Python :: 3.10
Classifier: Programming Language :: Python :: 3.11
Classifier: Topic :: Scientific/Engineering :: Artificial Intelligence
Classifier: Topic :: Games/Entertainment
Requires-Python: >=3.9
License-File: LICENSE
Requires-Dist: pyyaml>=6.0
Provides-Extra: dev
Requires-Dist: pytest>=7.0; extra == "dev"
Requires-Dist: pytest-cov>=4.0; extra == "dev"
Requires-Dist: black>=23.0; extra == "dev"
Requires-Dist: pylint>=2.17; extra == "dev"
Requires-Dist: mypy>=1.8; extra == "dev"
Requires-Dist: numpy>=1.24.0; extra == "dev"
Requires-Dist: scipy>=1.10.0; extra == "dev"
Requires-Dist: statsmodels>=0.14.0; extra == "dev"
Requires-Dist: matplotlib>=3.7.0; extra == "dev"
Requires-Dist: openai>=1.0; extra == "dev"
Requires-Dist: anthropic>=0.5; extra == "dev"
Requires-Dist: google-cloud-aiplatform>=1.70.0; extra == "dev"
Provides-Extra: openai
Requires-Dist: openai>=1.0; extra == "openai"
Provides-Extra: anthropic
Requires-Dist: anthropic>=0.5; extra == "anthropic"
Provides-Extra: google
Requires-Dist: google-cloud-aiplatform>=1.70.0; extra == "google"
Provides-Extra: providers
Requires-Dist: openai>=1.0; extra == "providers"
Requires-Dist: anthropic>=0.5; extra == "providers"
Requires-Dist: google-cloud-aiplatform>=1.70.0; extra == "providers"
Provides-Extra: research
Requires-Dist: numpy>=1.24.0; extra == "research"
Requires-Dist: scipy>=1.10.0; extra == "research"
Requires-Dist: statsmodels>=0.14.0; extra == "research"
Requires-Dist: matplotlib>=3.7.0; extra == "research"
Provides-Extra: all
Requires-Dist: openai>=1.0; extra == "all"
Requires-Dist: anthropic>=0.5; extra == "all"
Requires-Dist: google-cloud-aiplatform>=1.70.0; extra == "all"
Requires-Dist: numpy>=1.24.0; extra == "all"
Requires-Dist: scipy>=1.10.0; extra == "all"
Requires-Dist: statsmodels>=0.14.0; extra == "all"
Requires-Dist: matplotlib>=3.7.0; extra == "all"
Requires-Dist: pytest>=7.0; extra == "all"
Requires-Dist: pytest-cov>=4.0; extra == "all"
Requires-Dist: black>=23.0; extra == "all"
Requires-Dist: pylint>=2.17; extra == "all"
Requires-Dist: mypy>=1.8; extra == "all"
Dynamic: license-file
